tf_coil_coordinator/__init__.py
tf_coil_coordinator/core.py
tf_coil_coordinator-0.0.2.dist-info/LICENSE
tf_coil_coordinator-0.0.2.dist-info/METADATA
tf_coil_coordinator-0.0.2.dist-info/WHEEL
tf_coil_coordinator-0.0.2.dist-info/top_level.txt
tf_coil_coordinator-0.0.2.dist-info/RECORD
